tomtombrumbrum/__init__.py
tomtombrumbrum/tomtombrumbrum.py
tomtombrumbrum-0.0.29.dist-info/LICENSE.txt
tomtombrumbrum-0.0.29.dist-info/METADATA
tomtombrumbrum-0.0.29.dist-info/WHEEL
tomtombrumbrum-0.0.29.dist-info/top_level.txt
tomtombrumbrum-0.0.29.dist-info/RECORD
