Metadata-Version: 2.1
Name: tomtombrumbrum
Version: 0.0.29
Summary: TomTom API library
Author: Gabriele Trevisan
Author-email: <gabriele.3vi@gmail.com>
Keywords: python,tomtom,api,drive
Classifier: Development Status :: 1 - Planning
Classifier: Intended Audience :: Developers
Classifier: Programming Language :: Python :: 3
Classifier: Operating System :: Unix
Classifier: Operating System :: MacOS :: MacOS X
Classifier: Operating System :: Microsoft :: Windows
License-File: LICENSE.txt
Requires-Dist: requests
